asuna_api/__init__.py
asuna_api/client.py
asuna_api/http.py
asuna_api/image.py
asuna_api/minecraft.py
asuna_api-0.3.3.dist-info/LICENSE
asuna_api-0.3.3.dist-info/METADATA
asuna_api-0.3.3.dist-info/WHEEL
asuna_api-0.3.3.dist-info/top_level.txt
asuna_api-0.3.3.dist-info/RECORD
