Metadata-Version: 2.1
Name: asuna_api
Version: 0.3.3
Summary: An async python wrapper for the asuna api
Author-email: JDJG3493 <jdjgbot@gmail.com>
License: MIT
Project-URL: repository, https://github.com/Senarc-Studios/asuna_api
Keywords: wrapper,api,random
Classifier: Development Status :: 3 - Alpha
Classifier: Intended Audience :: Developers
Classifier: Topic :: Software Development :: Build Tools
Classifier: License :: OSI Approved :: MIT License
Classifier: Programming Language :: Python :: 3
Classifier: Programming Language :: Python :: 3.8
Classifier: Programming Language :: Python :: 3.9
Classifier: Programming Language :: Python :: 3.10
Classifier: Programming Language :: Python :: 3.11
Requires-Python: >=3.8
License-File: LICENSE
Requires-Dist: aiohttp
Requires-Dist: yarl
